ecooptimizer/README.md
ecooptimizer/__init__.py
ecooptimizer/__main__.py
ecooptimizer/_version.py
ecooptimizer/config.py
ecooptimizer/analyzers/__init__.py
ecooptimizer/analyzers/analyzer_controller.py
ecooptimizer/analyzers/ast_analyzer.py
ecooptimizer/analyzers/astroid_analyzer.py
ecooptimizer/analyzers/base_analyzer.py
ecooptimizer/analyzers/pylint_analyzer.py
ecooptimizer/analyzers/ast_analyzers/__init__.py
ecooptimizer/analyzers/ast_analyzers/detect_long_element_chain.py
ecooptimizer/analyzers/ast_analyzers/detect_long_lambda_expression.py
ecooptimizer/analyzers/ast_analyzers/detect_long_message_chain.py
ecooptimizer/analyzers/ast_analyzers/detect_repeated_calls.py
ecooptimizer/analyzers/astroid_analyzers/__init__.py
ecooptimizer/analyzers/astroid_analyzers/detect_string_concat_in_loop.py
ecooptimizer/api/__init__.py
ecooptimizer/api/__main__.py
ecooptimizer/api/app.py
ecooptimizer/api/error_handler.py
ecooptimizer/api/routes/__init__.py
ecooptimizer/api/routes/detect_smells.py
ecooptimizer/api/routes/refactor_smell.py
ecooptimizer/api/routes/show_logs.py
ecooptimizer/data_types/__init__.py
ecooptimizer/data_types/custom_fields.py
ecooptimizer/data_types/smell.py
ecooptimizer/data_types/smell_record.py
ecooptimizer/measurements/__init__.py
ecooptimizer/measurements/base_energy_meter.py
ecooptimizer/measurements/codecarbon_energy_meter.py
ecooptimizer/refactorers/__init__.py
ecooptimizer/refactorers/base_refactorer.py
ecooptimizer/refactorers/multi_file_refactorer.py
ecooptimizer/refactorers/refactorer_controller.py
ecooptimizer/refactorers/concrete/__init__.py
ecooptimizer/refactorers/concrete/list_comp_any_all.py
ecooptimizer/refactorers/concrete/long_element_chain.py
ecooptimizer/refactorers/concrete/long_lambda_function.py
ecooptimizer/refactorers/concrete/long_message_chain.py
ecooptimizer/refactorers/concrete/long_parameter_list.py
ecooptimizer/refactorers/concrete/member_ignoring_method.py
ecooptimizer/refactorers/concrete/repeated_calls.py
ecooptimizer-0.1.0.dist-info/licenses/LICENSE
ecooptimizer-0.1.0.dist-info/METADATA
ecooptimizer-0.1.0.dist-info/WHEEL
ecooptimizer-0.1.0.dist-info/entry_points.txt
ecooptimizer-0.1.0.dist-info/top_level.txt
ecooptimizer-0.1.0.dist-info/RECORD
