Metadata-Version: 2.4
Name: ecooptimizer
Version: 0.1.0
Summary: A source code eco optimizer
Author: Sevhena Walker, Mya Hussain, Nivetha Kuruparan, Ayushi Amin, Tanveer Brar
License: Copyright (c) 2024-2025 Ayushi Amin, Mya Hussain, Nivetha Kuruparan, Sevhena Walker, Tanveer Brar
Project-URL: Repository, https://github.com/ssm-lab/capstone--source-code-optimizer
Project-URL: Bug Tracker, https://github.com/ssm-lab/capstone--source-code-optimizer/issues
Requires-Python: >=3.9
License-File: LICENSE
Requires-Dist: pylint
Requires-Dist: rope
Requires-Dist: astor
Requires-Dist: codecarbon
Requires-Dist: asttokens
Requires-Dist: uvicorn
Requires-Dist: fastapi
Requires-Dist: pydantic
Requires-Dist: libcst
Requires-Dist: websockets
Provides-Extra: dev
Requires-Dist: pytest; extra == "dev"
Requires-Dist: pytest-cov; extra == "dev"
Requires-Dist: pytest-mock; extra == "dev"
Requires-Dist: ruff; extra == "dev"
Requires-Dist: coverage; extra == "dev"
Requires-Dist: pyright; extra == "dev"
Requires-Dist: pre-commit; extra == "dev"
Dynamic: license-file
